{
    "display": {
        "icon": {
            "item": "minecraft:beacon",
            "nbt": "{CustomModelData:1}"
        },
        "title": {
            "text": "Exclusive Death Pose",
            "color": "#ff0000",
            "bold": true
        },
        "frame": "challenge",
        "show_toast": true,
        "announce_to_chat": false,
        "description": {
            "text": "Complete this row of advancements to unlock.",
            "color": "dark_green",
            "bold": false
        }
    },
    "parent": "advancements:custom/recovery",
    "criteria": {
        "impossible": {
            "trigger": "minecraft:impossible"
        }
    }
}